{
  "1 Trong 2 Admin của website HoatHinh3D là ai ? (Biệt danh chính xác ở web)": "4. Từ Dương",
  "Ai là huynh đệ và cũng là người thầy mà Vương Lâm trong Tiên Nghịch kính trọng nhất ?": "2. Tư Đồ Nam",
  "Ai là mẹ của Đường Tam?": "3. A Ngân",
  "Ai là người đứng đầu Vũ Hồn Điện?": "4. Bỉ Bỉ Đông",
  "Ai là nhân vật chính trong bộ phim hoạt hình trung quốc Thần Mộ ?": "4. Thần Nam",
  "Bách Lý Đông Quân là nhân vật trong bộ hoạt hình trung quốc nào sau đây ?": "1. Thiếu Niên Bạch Mã Tuý Xuân Phong",
  "Bạch Nguyệt Khôi là tên nhân vật chính trong bộ phim hoạt hình trung quốc nào sau đây ?": "4. Linh Lung",
  "Bạch Tiểu Thuần là nhân vật chính trong bộ hoạt hình trung quốc nào ?": "4. Nhất Niệm Vĩnh Hằng",
  "Bạch Tiểu Thuần trong Nhất Niệm Vĩnh Hằng luôn được ai âm thầm giúp đỡ ?": "4. Đỗ Lăng Phỉ",
  "Bộ phim nào sau đây thuộc tiểu thuyết của tác giả Thiên Tằm Thổ Đậu": "4. Tất cả đáp án",
  "Các cấp bậc nào sau đây thuộc phim Đấu Phá Thương Khung ?": "4. Đấu Tông",
  "Cháu dượng của Bạch Tiểu Thuần trong Nhất Niệm Vĩnh Hằng là ai ?": "2. Tống Khuyết",
  "Chủ nhân đời trước của Vẫn Lạc Tâm Viêm trong Đấu Phá Thương Khung là ai ?": "Diệu Thiên Hoả",
  "Công pháp gì giúp Tiêu Viêm trong Đấu Phá Thương Khung hấp thụ nhiều loại dị hỏa ?": "3. Phần Quyết",
  "Công pháp nào sau đây là của Hàn Lập trong Phàm Nhân Tu Tiên ?": "Tất cả đáp án",
  "Cơ Tử Nguyệt là nhân vật trong các bộ hoạt hình trung quốc nào sau đây ?": "3. Già Thiên",
  "Dạ Táng còn là biệt danh của ai trong Nhất Niệm Vĩnh Hằng ?": "3. Bạch Tiểu Thuần",
  "Danh xưng Tàn Thi Bại Thuế là của nhân vật nào trong Hoạ Giang Hồ Chi Bất Lương Nhân ?": "2. Hàng Thần",
  "Diễm Linh Cơ là nhân vật trong phim hoạt hình trung quốc nào ?": "3. Thiên Hành Cửu Ca",
  "Diệp Phàm là nhân vật chính trong bộ hoạt hình trung quốc nào ?": "3. Già Thiên",
  "Diệp Thần trong Tiên Võ Đế Tôn gia nhập Tông Môn nào đầu tiên ?": "2. Chính Dương Tông",
  "Dược Trần trong Đấu Phá Thương Khung đã từng bị đồ đệ nào phản bội ?": "3. Hàn Phong",
  "Đại ca của Tiêu Viêm trong Đấu Phá Thương Khung tên gì ?": "4. Tiêu Đỉnh",
  "Đàm Vân là nhân vật chính trong bộ phim hoạt hình trung quốc nào sau đây ?": "2. Nghịch Thiên Chí Tôn",
  "Đạo lữ của Hàn Lập là ai ?": "4. Nam Cung Uyển",
  "Đâu là nhân vật chính trong phim Bách Luyện Thành Thần ?": "3. La Chinh",
  "Đâu là Thái Cổ Thập Hung trong phim Thế Giới Hoàn Mỹ ?": "Tất cả đáp án",
  "Đâu là tuyệt kỹ số 1 Hạo Thiên Tông mà Đường Hạo dạy cho con trai trong Đấu La Đại Lục ?": "1. Đại Tu Di Chùy",
  "Đấu Sát Toàn Viên Kiếm là một kỹ năng trong bộ phim hoạt hình trung quốc nào ?": "Thần Ấn Vương Tọa",
  "Độc Cô Bác trong Đấu La Đại Lục có vũ hồn gì ?": "2. Bích Lân Xà",
  "Em trai ruột của Thạch Hạo trong Thế Giới Hoàn Mỹ là ai ?": "2. Tần Hạo",
  "Hàn lập sở hữu những vật phẩm nào dưới đây ?": "1. Thanh Trúc Phong Vân Kiếm",
  "Hàn Lập trong Phàm Nhân Tu Tiên đến Thất Huyền Môn bái ai làm thầy ?": "1. Mặc Đại Phu",
  "Hàn Lập trong Phàm Nhân Tu Tiên gia nhập môn phái nào đầu tiên ?": "1. Thất Huyền Môn",
  "Hàn Lập trong Phàm Nhân Tu Tiên từng cứu ai mà bị hấp thụ tu vi giảm xuống Luyện Khí Kỳ ?": "3. Nam Cung Uyển",
  "Hoang Thiên Đế là nhân vật chính trong bộ phim hoạt hình trung quốc nổi tiếng nào ?": "4. Thế Giới Hoàn Mỹ",
  "Hoắc Vũ Hạo là hậu nhân của ai trong Sử Lai Khắc ?": "4. Đái Mộc Bạch",
  "Hồn hoàn màu nào mạnh nhất?": "4. Đỏ",
  "Huân Nhi là công chúa của bộ tộc nào?": "3. Cổ Tộc",
  "Khi ở Già Nam Học Viện, Tiêu Viêm thu phục được loại dị hỏa nào ?": "3. Vẫn Lạc Tâm Viêm",
  "Kính Huyền trong Quyến Tư Lượng là hậu duệ của tộc nào ?": "4. Thần Tộc",
  "Lạc Ly trong Đại Chúa Tể là nhân vật trong Tộc nào ?": "3. Lạc Thần Tộc",
  "Lâm Động trong Vũ Động Càn Khôn học được Linh Võ Học nào khi vào bia cổ Đại Hoang ?": "2. Đại Hoang Tù Thiên Chỉ",
  "Lâm Động trong Vũ Động Càn Khôn luyện hóa Tổ Phù nào đầu tiên ?": "2. Thôn Phệ Tổ Phù",
  "Lâm Động trong Vũ Động Càn Khôn sử dụng vũ khí loại nào sau đây ?": "3. Thương",
  "Lâm Phong là nhân vật trong bộ hoạt hình trung quốc nào sau đây ?": "4. Vạn Giới Độc Tôn",
  "Lâm Thất Dạ là nhân vật trong bộ phim hoạt hình trung quốc nào sau đây ?": "2. Trảm Thần",
  "Lâm Thất Dạ trong Trảm Thần sở hữu sức mạnh của vị thần nào ?": "1. Thiên Sứ",
  "Long Tuyền Kiếm xuất hiện trong bộ phim hoạt hình nào dưới đây ?": "3. Họa Giang Hồ Chi Bất Lương Nhân",
  "Lục Tuyết Kỳ trong Tru Tiên thuộc Phong nào trong Thanh Vân Môn?": "1. Tiểu Trúc Phong",
  "Lý Tinh Vân trong Họa Giang Hồ Chi Bất Lương Nhân sử dụng vũ khí nào sau đây ?": "3. Long Tuyền Kiếm",
  "Lý Trường Thọ trong Sư Huynh A Sư Huynh xuyên không về Hồng Hoang bái sư ở đâu ?": "2. Độ Tiên Môn",
  "Man Hồ Tử trong phim \"Phàm Nhân Tu Tiên\" tu luyện công pháp nào?": "1. Thác Thiên Ma Công",
  "Mẫu thân của La Phong trong Thôn Phệ Tinh Không tên là gì ?": "4. Cung Tâm Lan",
  "Mẹ của Mạnh Xuyên trong Thương Nguyên Đồ tên là gì ?": "2. Bạch Niệm Vân",
  "Mẹ của Tần Trần là ai ?": "4. Tần Nguyệt Trì",
  "Mẹ của Thạch Hạo trong Thế Giới Hoàn Mỹ tên là gì": "4. Tần Di Ninh",
  "Mối tình đầu của Diệp Thần trong Tiên Võ Đế Tôn là ai ?": "3. Cơ Ngưng Sương",
  "Mục đích tu luyện của Vương Lâm trong Tiên Nghịch theo diễn biến phim hiện tại là gì ?": "2. Báo Thù",
  "Mục Trần trong Đại Chúa Tể liên kết Huyết Mạch với ?": "2. Cửu U Tước",
  "Mục Vân là nhân vật trong bộ hoạt hình trung quốc nào sau đây ?": "4. Vô Thượng Thần Đế",
  "Nam chính trong bộ hoạt hình trung quốc Ám Hà Truyện là ai ?": "4. Tô Mộ Vũ",
  "Nam chính trong bộ Quyến Tư Lượng là ai ?": "2. Kính Huyền",
  "Nghịch Hà Tông là Tông Môn trong bộ hoạt hình trung quốc nào sau đây ?": "1. Nhất Niệm Vĩnh Hằng",
  "Nghịch Thiên Nhi Hành là một nhân vật trong bộ phim hh3d nào sau đây ?": "3. Vũ Canh Kỷ",
  "Ngụy Anh (Ngụy Vô Tiện) là nhân vật trong bộ hhtq nào sau đây ?": "3. Ma Đạo Tổ Sư",
  "Người bạn thuở nhỏ của Trương Tiểu Phàm trong Tru Tiên là ai ?": "2. Lâm Kinh Vũ",
  "Nhân vật Bách Lý Đồ Minh xuất hiện trong phim hoạt hình nào dưới đây ?": "4. Trảm Thần Chi Phàm Trần Thần Vực",
  "Nhân vật chính của \"Thần Ấn Vương Tọa\" là ai?": "1. Long Hạo Thần",
  "Nhân vật chính của Đấu La Đại Lục là ai?": "2. Đường Tam",
  "Nhân vật chính Lý Trường Thọ trong Sư Huynh A Sư Huynh đã tỏ tình với ai ?": "3. Vân Tiêu",
  "Nhân vật chính trong Thương Nguyên đồ là ai ?": "4. Mạnh Xuyên",
  "Nhân vật chính trong Yêu Thần Ký tên là gì ?": "4. Nhiếp Ly",
  "Nhân vật nào luôn bất bại trong phim Hoạt Hình Trung Quốc, được ví như One-Punch Man ?": "2. Từ Dương",
  "Nhân vật nào sau đây được mệnh danh là Vua Lỳ Đòn trong Đấu Phá Thương Khung ?": "1. Phượng Thanh Nhi",
  "Nhị ca của Tiêu Viêm trong Đấu Phá Thương Khung tên gì ?": "1. Tiêu Lệ",
  "Nhiếp Phong là nhân vật chính trong phim hoạt hình trung quốc nào ?": "3. Chân Võ Đỉnh Phong",
  "Ninh Diêu là một nhân vật trong bộ phim hoạt hình trung quốc nào sau đây ?": "3. Kiếm Lai",
  "Nữ chính cũng là vợ Đông Bá Tuyết Ưng trong Tuyết Ưng Lĩnh Chủ là ai sau đây ?": "1. Dư Tĩnh Thu",
  "Nữ chính trong bộ Quyến Tư Lượng là ai ?": "3. Đồ Lệ",
  "Ông nội của Lâm Động trong Vũ Động Càn Khôn là ai ?": "4. Lâm Chấn Thiên",
  "Phụ Thân của Lâm Động trong Vũ Động Càn Khôn là ai ?": "3. Lâm Khiếu",
  "Phương Hàn là nhân vật trong bộ hoạt hình trung quốc nào sau đây ?": "1. Vĩnh Sinh",
  "Phương Hàn trong Vĩnh Sinh nhận được Giao Phục Hoàng Tuyền Đồ từ ai ?": "3. Bạch Hải Thiện",
  "Phương Hàn trong Vĩnh Sinh xuất thân là gì ở nhà họ Phương ?": "2. Nô Bộc",
  "Phượng Thanh Nhi trong Đấu Phá Thương Khung thuộc chủng tộc nào ?": "2. Thiên Yêu Hoàng Tộc",
  "Số hiệu vị thần của main trong Trảm Thần: Phàm Trần Thần Vực là số mấy ?": "2. 003",
  "Sử Lai Khắc Thất Quái đã từng đến nơi nào để luyện tập?": "1. Hải Thần Đảo",
  "Sư mẫu của Bạch Tiểu Thuần trong Nhất Niệm Vĩnh Hằng là ai ?": "1. Hứa Mị Nương",
  "Sư phụ của Bạch Tiểu Thuần trong Nhất Niệm Vĩnh Hằng là ai ?": "3. Lý Thanh Hậu",
  "Sư phụ của Lý Trường Thọ là ai ?": "3. Tề Nguyên",
  "Sư phụ mà Diệp Thần yêu trong Tiên Võ Đế Tôn là ai ?": "2. Sở Huyên Nhi",
  "Sư Phụ thứ 2 của Lý Trường Thọ trong phim ": "2. Thái Thanh Thánh Nhân",
  "Tại sao Đường Tam bị Đường Môn truy sát ở tập đầu phim Đấu La Đại Lục ?": "3. Học trộm tuyệt học bổn môn",
  "Tần Vũ trong Tinh Thần Biến được tặng pháp bảo siêu cấp vip pro nào để tu luyện nhanh chóng ?": "1. Khương Lan Tháp",
  "Tần Vũ trong Tinh Thần Biến khiếm khuyết đan điền nhờ đâu mới có thể tu luyện ?": "4. Lưu Tinh Lệ",
  "Thánh nữ nào trong Già Thiên bị nhân vật chính Diệp Phàm lấy mất cái áo lót ?": "2. Diêu Hi",
  "Thần Thông Bí Cảnh xuất hiện trong bộ phim hoạt hình nào dưới đây ?": "4. Vĩnh Sinh",
  "Thần vị mà Đường Tam đạt được là gì?": "2. Hải Thần và Tu La Thần",
  "Thế lực nào là đối thủ lớn nhất của Tiêu Viêm trong Đấu Phá Thương Khung?": "1. Hồn Điện",
  "Thú cưng Thôn Thôn trong Nguyên Tôn sinh ra có sức mạnh ngang cảnh giới nào ?": "1. Thái Sơ Cảnh",
  "Tiêu Khinh Tuyết xuất hiện trong bộ hoạt hình nào dưới đây ?": "3. Tuyệt Thế Chiến Hồn",
  "Tiêu Viêm đã lập nên thế lực nào khi ở Học Viện Già Nam ?": "3. Bàn Môn",
  "Tiêu Viêm trong Đấu Phá Thương Khung đã Hẹn Ước 3 Năm với ai ?": "4. Nạp Lan Yên Nhiên",
  "Tiêu Viêm trong Đấu Phá Thương Khung sử dụng loại vũ khí nào sau đây ?": "4. Thước",
  "Tiêu Viêm trong Đấu Phá Thương Khung thuộc gia tộc nào?": "2. Tiêu Gia",
  "Tình đầu của Diệp Phàm trong Già Thiên là ai ?": "4. Lý Tiểu Mạn",
  "Trần Bình An là nam chính trong bộ phim hoạt hình trung quốc nào ?": "1. Kiếm Lai",
  "Triệu Ngọc Chân là nhân vật trong bộ hoạt hình trung quốc nào sau đây ?": "Thiếu Niên Bạch Mã Tuý Xuân Phong",
  "Trong bộ Đấu Phá Thương Khung, Tiêu Viêm tìm đến ai để cứu Dược Lão ?": "1. Phong Tôn Giả",
  "Trong bộ Tiên Nghịch, nhân vật chính Vương Lâm khi ở quê nhà còn có tên khác là gì ?": "2. Thiết Trụ",
  "Trong Đấu La Đại Lục, Đường Hạo là gì của Đường Tam?": "2. Cha",
  "Trong Già Thiên, thể chất Diệp Phàm là thể chất gì ?": "2. Hoang Cổ Thánh Thể",
  "Trong Phàm Nhân Tu Tiên ai bị luyện thành khôi lỗi Khúc Hồn ?": "3. Trương Thiết",
  "Trong phim Tiên Nghịch, Vương Lâm vô tình có được pháp bảo nghịch thiên nào ?": "3. Thiên Nghịch Châu",
  "Trong Tiên Nghịch, Vương Lâm nhận được truyền thừa gì ở Cổ Thần Chi Địa ?": "4. Ký Ức",
  "Trong Tru Tiên, Điền Bất Dịch là thủ tọa của Phong nào?": "4. Đại Trúc Phong",
  "Trong Vĩnh Sinh - Phương Hàn hẹn ước 10 năm cùng với ai ?": "3. Hoa Thiên Đô",
  "Trước khi đến Linh Khê Tông, Bạch Tiểu Thuần trong Nhất Niệm Vĩnh Hằng ở đâu ?": "2. Mạo Nhi Sơn Thôn",
  "Trương Tiểu Phàm trong phim Tru Tiên còn có tên gọi là ?": "1. Quỷ Lệ",
  "Trương Tiểu Phàm trong Tru Tiên từng được nhận vào môn phái nào?": "2. Thanh Vân Môn",
  "Tử Nghiên trong Đấu Phá Thương Khung thuộc chủng tộc nào ?": "3. Thái Hư Cổ Long",
  "Vân Triệt là tên nhân vật chính trong bộ phim hoạt hình trung quốc nào sau đây ?": "3. Nghịch Thiên Tà Thần",
  "Vũ Canh là nhân vật trong bộ hoạt hình trung quốc nào sau đây ?": "2. Vũ Canh Kỷ",
  "Vũ hồn của Chu Trúc Thanh là gì?": "4. U Minh Linh Miêu",
  "Vũ hồn của Đới Mộc Bạch là gì?": "1. Bạch Hổ",
  "Vũ hồn của Mã Hồng Tuấn là gì?": "3. Hỏa Phượng Hoàng",
  "Vũ hồn của Tiểu Vũ là gì?": "3. Nhu Cốt Thỏ",
  "Vũ hồn thứ hai của Đường Tam là gì?": "2. Hạo Thiên Chùy",
  "Vũ khí của Đàm Vân trong Nghịch Thiên Chí Tôn là gì ?": "1. Hồng Mông Thần Kiếm",
  "Vũ khí mà Tiêu Viêm trong Đấu Phá Thương Khung luôn mang bên mình có tên gọi là gì ?": "3. Huyền Trọng Xích",
  "Vương Lâm trong phim Tiên Nghịch dựa vào gì để vô địch cùng cảnh giới ?": "1. Cực Cảnh",
  "Y Lai Khắc Tư là một nhân vật trong bộ phim hoạt hình trung quốc nào sau đây ?": "3. Cả 1 và 2",
  "Ai là người thầy của Đường Tam?": "2. Đại Sư",
  "Thiên Hoả Tôn Giả trong Đấu Phá Thương Khung dùng thi thể của ai để hồi sinh ?": "4.Vân Sơn",
  "Lâm Thất Dạ là nhân vật trong bộ hoạt hình trung quốc nào sau đây ?": "2. Trảm Thần",
  "Ám tinh giới được xuất hiện trong bộ phim hoạt hình nào dưới đây ?": "3. Tinh Thần Biến",
  "Tỉnh Cửu là nhân vật chính trong bộ phim hoạt hình trung quốc nào sau đây ?": "2. Đại Đạo Triều Thiên",
  "Lý Tinh Vân là một nhân vật trong bộ phim hoạt hình trung quốc nào sau đây ?": "1. Họa Giang Hồ Chi Bất Lương Nhân",
  "Tần Mục là nhân vật chính trong bộ phim hoạt hình trung quốc nào sau đây ?": "4. Mục Thần Ký",
  "Tiêu Thần là nhân vật chính trong bộ phim hoạt hình trung quốc nào sau đây ?": "Trường Sinh Giới",
  "Tần Nam là nhân vật chính trong bộ hoạt hình trung quốc nào sau đây ?": "3. Tuyệt Thế Chiến Hồn",
  "Test": "Test",
  "Mục đích chính tu luyện của Tần Vũ trong Tinh Thần Biến là gì ??": "3. Vì muốn được cưới Khương Lập",
  "Khô Lâu Đà Chủ xuất hiện trong bộ phim hoạt hình nào dưới đây ?": "4. Võ Thần Chúa Tể",
  "Nhân vật chính trong Man Hoang Tiên Giới là ai ?": "2. Lục Hàng Chi",
  "Mục đích tu luyện của Tần Vũ trong Tinh Thần Biến là gì?": "Vì muốn được cưới Khương Lập",
  "Nhân vật chính trong Quân Tử Vô Tật là ai?": "Dao Cơ",
  "Nhân vật chính trong Đấu Chiến Thiên Hạ là ai?": "Đại Phong",
  "Nhân vật chính trong Ta Có Thể Giác Ngộ Vô Hạn là ai?": "Tiêu Vân",
  "Tần Mục trong Mục Thần Ký lớn lên ở đâu?": "Tàn Lão Thôn",
  "xxxx": "xx",
  "xxxx": "xx",
  "xxxx": "xx",
  "xxxx": "xx",
  "xxxx": "xx",
  "xxxx": "xx",
  "Tại sao Hàn Lập khi gặp Phong Hi không chạy mà ở lại giúp đỡ chế tạo Phong Lôi Sí ?": "4. Vì đánh không lại"
}
